azure_blob_operations/__init__.py
azure_blob_operations/blob_operations.py
azure_blob_operations/config.py
azure_blob_operations/utils.py
azure_blob_operations-0.1.2.dist-info/METADATA
azure_blob_operations-0.1.2.dist-info/WHEEL
azure_blob_operations-0.1.2.dist-info/top_level.txt
azure_blob_operations-0.1.2.dist-info/RECORD
