Metadata-Version: 2.1
Name: azure-blob-operations
Version: 0.1.2
Summary: A utility package for generic Azure Blob Storage operations
Author: Uday Pallati
Author-email: udaypallati123@gmail.com
Classifier: Programming Language :: Python :: 3
Classifier: License :: OSI Approved :: MIT License
Classifier: Operating System :: OS Independent
Requires-Python: >=3.11.5
Requires-Dist: azure-storage-blob>=12.23.1
